tests/__init__.py
tests/settings.py
tests/test_json.py
tests/test_templates.py
tests/app/__init__.py
tests/app/models.py
tests/app/urls.py
tests/app/migrations/0001_initial.py
tests/app/migrations/__init__.py
wagtailschemaorg/__init__.py
wagtailschemaorg/_version.py
wagtailschemaorg/encoder.py
wagtailschemaorg/jinja2tags.py
wagtailschemaorg/jsonld.py
wagtailschemaorg/models.py
wagtailschemaorg/registry.py
wagtailschemaorg/templates.py
wagtailschemaorg/utils.py
wagtailschemaorg/templatetags/__init__.py
wagtailschemaorg/templatetags/wagtailschemaorg_tags.py
wagtail_schema.org-4.1.1.dist-info/LICENSE
wagtail_schema.org-4.1.1.dist-info/METADATA
wagtail_schema.org-4.1.1.dist-info/WHEEL
wagtail_schema.org-4.1.1.dist-info/top_level.txt
wagtail_schema.org-4.1.1.dist-info/RECORD
