Metadata-Version: 2.1
Name: wagtail-schema.org
Version: 4.1.1
Summary: Add Schema.org JSON-LD to your website
Home-page: https://github.com/takeflight/wagtail-schema.org
Author: Tim Heap
Author-email: tim@takeflight.com.au
License: BSD License
Platform: UNKNOWN
Classifier: Environment :: Web Environment
Classifier: Intended Audience :: Developers
Classifier: Operating System :: OS Independent
Classifier: Programming Language :: Python
Classifier: Programming Language :: Python :: 3
Classifier: Programming Language :: Python :: 3.7
Classifier: Programming Language :: Python :: 3.8
Classifier: Programming Language :: Python :: 3.9
Classifier: Programming Language :: Python :: 3.10
Classifier: Framework :: Django
Classifier: Framework :: Django :: 3
Classifier: Framework :: Django :: 3.2
Classifier: Framework :: Django :: 4
Classifier: Framework :: Django :: 4.0
Classifier: Framework :: Django :: 4.1
Classifier: Framework :: Wagtail
Classifier: Framework :: Wagtail :: 4
Classifier: License :: OSI Approved :: BSD License
License-File: LICENSE
Requires-Dist: wagtail (>=4.1)
Provides-Extra: testing
Requires-Dist: jinja2 (<3.0,>=2.10) ; extra == 'testing'
Requires-Dist: markupsafe (==2.0.1) ; extra == 'testing'
